pyseg.cp37-win_amd64.pyd
pyseg-0.0.9.dist-info/LICENCE
pyseg-0.0.9.dist-info/METADATA
pyseg-0.0.9.dist-info/WHEEL
pyseg-0.0.9.dist-info/top_level.txt
pyseg-0.0.9.dist-info/RECORD
