Metadata-Version: 1.2
Name: pyseg
Version: 0.0.9
Summary: sentence seg module written in C
Home-page: https://github.com/wbq813/pyseg
Author: wbq813
Author-email: wbq813@foxmail.com
License: MIT
Platform: linux
Classifier: Development Status :: 4 - Beta
Classifier: Intended Audience :: Developers
Classifier: Intended Audience :: Science/Research
Classifier: License :: OSI Approved :: MIT License
Classifier: Programming Language :: Python :: 3.5
Classifier: Programming Language :: Python :: 3.6
Classifier: Topic :: Software Development
Classifier: Topic :: Software Development :: Libraries :: Python Modules
Classifier: Topic :: Scientific/Engineering
Classifier: Topic :: Scientific/Engineering :: Information Analysis
Classifier: Topic :: Text Processing :: Linguistic
Requires-Python: >=3.5
